update_chromedriver/chromedriver_update.py
update_chromedriver_package-1.1.1.dist-info/METADATA
update_chromedriver_package-1.1.1.dist-info/WHEEL
update_chromedriver_package-1.1.1.dist-info/licenses/LICENSE
update_chromedriver_package-1.1.1.dist-info/RECORD
