Metadata-Version: 2.1
Name: update_chromedriver_package
Version: 1.1.1
Summary: Comprueba la versión actual del Google Chrome y descarga o actualiza el chromedriver. En Linux y MacOS
Project-URL: Homepage, https://github.com/Pistatxos/update_chromedriver_package
Author: Mario x
License: MIT License
License-File: LICENSE
Classifier: License :: OSI Approved :: MIT License
Classifier: Operating System :: OS Independent
Classifier: Programming Language :: Python :: 3
Requires-Python: >=3.9
